{
    "key": "group_696f5c1c8d9f2",
    "title": "Block - FAQ",
    "fields": [
        {
            "key": "field_696f5a1c8d9f0",
            "label": "Title",
            "name": "title",
            "aria-label": "",
            "type": "text",
            "instructions": "",
            "required": 0,
            "conditional_logic": 0,
            "wrapper": {
                "width": "",
                "class": "",
                "id": ""
            },
            "default_value": "",
            "maxlength": "",
            "placeholder": "",
            "prepend": "",
            "append": ""
        },
        {
            "key": "field_696f5a2c8d9f1",
            "label": "FAQ items",
            "name": "faq_items",
            "aria-label": "",
            "type": "repeater",
            "instructions": "Add question and answer pairs",
            "required": 0,
            "conditional_logic": 0,
            "wrapper": {
                "width": "",
                "class": "",
                "id": ""
            },
            "layout": "block",
            "pagination": 0,
            "min": 0,
            "max": 0,
            "collapsed": "",
            "button_label": "Add item",
            "rows_per_page": 20,
            "sub_fields": [
                {
                    "key": "field_696f5a3c8d9f2",
                    "label": "Question",
                    "name": "question",
                    "aria-label": "",
                    "type": "text",
                    "instructions": "",
                    "required": 0,
                    "conditional_logic": 0,
                    "wrapper": {
                        "width": "",
                        "class": "",
                        "id": ""
                    },
                    "default_value": "",
                    "maxlength": "",
                    "placeholder": "",
                    "prepend": "",
                    "append": "",
                    "parent_repeater": "field_696f5a2c8d9f1"
                },
                {
                    "key": "field_696f5a4c8d9f3",
                    "label": "Answer",
                    "name": "answer",
                    "aria-label": "",
                    "type": "textarea",
                    "instructions": "",
                    "required": 0,
                    "conditional_logic": 0,
                    "wrapper": {
                        "width": "",
                        "class": "",
                        "id": ""
                    },
                    "default_value": "",
                    "translations": "translate",
                    "maxlength": "",
                    "rows": "",
                    "placeholder": "",
                    "new_lines": "",
                    "parent_repeater": "field_696f5a2c8d9f1"
                }
            ]
        }
    ],
    "location": [
        [
            {
                "param": "block",
                "operator": "==",
                "value": "acf\/block-faq"
            }
        ]
    ],
    "menu_order": 0,
    "position": "normal",
    "style": "default",
    "label_placement": "top",
    "instruction_placement": "label",
    "hide_on_screen": "",
    "active": true,
    "description": "",
    "show_in_rest": 0,
    "modified": 1779025784
}